{
  "bids_meta": {
    "EchoTime": 0.037,
    "FlipAngle": 8,
    "ParallelAcquisitionTechnique": "SENSE",
    "ParallelReductionFactorInPlan": [
      1,
      1.5
    ],
    "PhaseEncodingDirection": [
      "i-",
      "j-"
    ],
    "PulseSequenceType": "3D fast-field echo",
    "RepetitionTime": 0.081,
    "WaterFatShift": 2.268,
    "dataset": "unknown",
    "modality": "T1w",
    "run_id": 2,
    "subject_id": "0781"
  },
  "cjv": 0.5892847677685755,
  "cnr": 2.1036599575324173,
  "efc": 0.7676042876689427,
  "fber": 5212.404296875,
  "fwhm_avg": 4.246326666666667,
  "fwhm_x": 4.17998,
  "fwhm_y": 4.5307,
  "fwhm_z": 4.0283,
  "icvs_csf": 0.22477592222361048,
  "icvs_gm": 0.42276077802625983,
  "icvs_wm": 0.3524632997501297,
  "inu_med": 0.9963147044181824,
  "inu_range": 0.3916473984718323,
  "provenance": {
    "md5sum": "ee369f56250a9380890e1d34aea007e7",
    "settings": {
      "testing": false
    },
    "software": "mriqc",
    "version": "0.15.0",
    "warnings": {
      "large_rot_frame": true,
      "small_air_mask": false
    },
    "webapi_port": null,
    "webapi_url": "https://mriqc.nimh.nih.gov/api/v1"
  },
  "qi_1": 0.0,
  "qi_2": 0.022226394392450426,
  "rpve_csf": 20.394033908678434,
  "rpve_gm": 11.162488024810967,
  "rpve_wm": 15.592216094973358,
  "size_x": 160,
  "size_y": 256,
  "size_z": 256,
  "snr_csf": 3.4811532755251324,
  "snr_gm": 10.051348500329798,
  "snr_total": 13.336840450764205,
  "snr_wm": 26.47801957643768,
  "snrd_csf": 36.7500925493699,
  "snrd_gm": 75.44791162219117,
  "snrd_total": 68.38157663992764,
  "snrd_wm": 92.94672574822185,
  "spacing_x": 1.0,
  "spacing_y": 1.0,
  "spacing_z": 1.0,
  "summary_bg_k": 4.095044672116504,
  "summary_bg_mad": 7.0486249923706055,
  "summary_bg_mean": 7.807520389556885,
  "summary_bg_median": 4.754225254058838,
  "summary_bg_n": 446490.0,
  "summary_bg_p05": 0.0,
  "summary_bg_p95": 23.816627407073973,
  "summary_bg_stdv": 7.829343795776367,
  "summary_csf_k": 0.6672575176181224,
  "summary_csf_mad": 94.51498413085938,
  "summary_csf_mean": 421.25396728515625,
  "summary_csf_median": 395.39495849609375,
  "summary_csf_n": 40354.0,
  "summary_csf_p05": 278.8276123046875,
  "summary_csf_p95": 640.8849060058594,
  "summary_csf_stdv": 113.58019256591797,
  "summary_gm_k": 0.03491020483712548,
  "summary_gm_mad": 76.4389877319336,
  "summary_gm_mean": 820.9169311523438,
  "summary_gm_median": 811.7455444335938,
  "summary_gm_n": 27285.0,
  "summary_gm_p05": 701.7849365234375,
  "summary_gm_p95": 971.3420532226562,
  "summary_gm_stdv": 80.75838470458984,
  "summary_wm_k": 0.8031352097487265,
  "summary_wm_mad": 34.50570297241211,
  "summary_wm_mean": 999.6658935546875,
  "summary_wm_median": 1000.015625,
  "summary_wm_n": 224733.0,
  "summary_wm_p05": 936.8534301757813,
  "summary_wm_p95": 1060.792041015625,
  "summary_wm_stdv": 37.76768112182617,
  "tpm_overlap_csf": 0.22334784269332886,
  "tpm_overlap_gm": 0.502602756023407,
  "tpm_overlap_wm": 0.5443437099456787,
  "wm2max": 0.6366561699298198
}