{
  "bids_meta": {
    "EchoTime": 0.037,
    "FlipAngle": 8,
    "ParallelAcquisitionTechnique": "SENSE",
    "ParallelReductionFactorInPlan": [
      1,
      1.5
    ],
    "PhaseEncodingDirection": [
      "i-",
      "j-"
    ],
    "PulseSequenceType": "3D fast-field echo",
    "RepetitionTime": 0.081,
    "WaterFatShift": 2.268,
    "dataset": "unknown",
    "modality": "T1w",
    "run_id": 3,
    "subject_id": "0607"
  },
  "cjv": 0.574583753680892,
  "cnr": 2.2567911922153248,
  "efc": 0.6822257794259527,
  "fber": 33359.56640625,
  "fwhm_avg": 4.242906666666666,
  "fwhm_x": 4.15418,
  "fwhm_y": 4.49889,
  "fwhm_z": 4.07565,
  "icvs_csf": 0.1986175884373861,
  "icvs_gm": 0.4467100190978062,
  "icvs_wm": 0.3546723924648077,
  "inu_med": 0.9148040413856506,
  "inu_range": 0.39207313060760507,
  "provenance": {
    "md5sum": "7110a188cb2e0d9f26378d8475900d43",
    "settings": {
      "testing": false
    },
    "software": "mriqc",
    "version": "0.15.0",
    "warnings": {
      "large_rot_frame": true,
      "small_air_mask": false
    },
    "webapi_port": null,
    "webapi_url": "https://mriqc.nimh.nih.gov/api/v1"
  },
  "qi_1": 0.006644706396921136,
  "qi_2": 0.06578139956977673,
  "rpve_csf": 23.361514705717205,
  "rpve_gm": 11.347952125874757,
  "rpve_wm": 16.166892378306184,
  "size_x": 160,
  "size_y": 256,
  "size_z": 256,
  "snr_csf": 3.1306460698577956,
  "snr_gm": 11.208417323119637,
  "snr_total": 11.886165045298123,
  "snr_wm": 21.31943174291694,
  "snrd_csf": 46.40932131456143,
  "snrd_gm": 90.16552220349296,
  "snrd_total": 82.815389058098,
  "snrd_wm": 111.87132365623964,
  "spacing_x": 1.0,
  "spacing_y": 1.0,
  "spacing_z": 1.0,
  "summary_bg_k": 8.977594469903812,
  "summary_bg_mad": 5.856189727783203,
  "summary_bg_mean": 4.1478271484375,
  "summary_bg_median": 3.991568088531494,
  "summary_bg_n": 580132.0,
  "summary_bg_p05": 0.0,
  "summary_bg_p95": 11.954777717590332,
  "summary_bg_stdv": 4.555087566375732,
  "summary_csf_k": 34.217942414403524,
  "summary_csf_mad": 116.18402099609375,
  "summary_csf_mean": 443.2843322753906,
  "summary_csf_median": 414.84765625,
  "summary_csf_n": 23019.0,
  "summary_csf_p05": 290.39996032714845,
  "summary_csf_p95": 652.618359375,
  "summary_csf_stdv": 132.5089569091797,
  "summary_gm_k": -0.07078796720439673,
  "summary_gm_mad": 72.18717956542969,
  "summary_gm_mean": 808.7545776367188,
  "summary_gm_median": 805.9793701171875,
  "summary_gm_n": 32963.0,
  "summary_gm_p05": 695.8856323242187,
  "summary_gm_p95": 932.38232421875,
  "summary_gm_stdv": 71.90731048583984,
  "summary_wm_k": 1.230372280543273,
  "summary_wm_mad": 39.29683303833008,
  "summary_wm_mean": 995.5511474609375,
  "summary_wm_median": 1000.0050659179688,
  "summary_wm_n": 206117.0,
  "summary_wm_p05": 905.4661254882812,
  "summary_wm_p95": 1062.460986328125,
  "summary_wm_stdv": 46.90568923950195,
  "tpm_overlap_csf": 0.2240709811449051,
  "tpm_overlap_gm": 0.5110532641410828,
  "tpm_overlap_wm": 0.5187113285064697,
  "wm2max": 0.6464594602409414
}