{
  "bids_meta": {
    "EchoTime": 0.037,
    "FlipAngle": 8,
    "ParallelAcquisitionTechnique": "SENSE",
    "ParallelReductionFactorInPlan": [
      1,
      1.5
    ],
    "PhaseEncodingDirection": [
      "i-",
      "j-"
    ],
    "PulseSequenceType": "3D fast-field echo",
    "RepetitionTime": 0.081,
    "WaterFatShift": 2.268,
    "dataset": "unknown",
    "modality": "T1w",
    "run_id": 3,
    "subject_id": "0215"
  },
  "cjv": 0.3962501930728318,
  "cnr": 3.1789145805238177,
  "efc": 0.6580445892384054,
  "fber": 24101.5546875,
  "fwhm_avg": 4.32262,
  "fwhm_x": 4.26667,
  "fwhm_y": 4.66266,
  "fwhm_z": 4.03853,
  "icvs_csf": 0.197803658100585,
  "icvs_gm": 0.44137765167678134,
  "icvs_wm": 0.36081869022263363,
  "inu_med": 1.6012896299362183,
  "inu_range": 0.5482278406620025,
  "provenance": {
    "md5sum": "abe74fb0676cb5772a53a5dc167c3ce8",
    "settings": {
      "testing": false
    },
    "software": "mriqc",
    "version": "0.15.0",
    "warnings": {
      "large_rot_frame": true,
      "small_air_mask": false
    },
    "webapi_port": null,
    "webapi_url": "https://mriqc.nimh.nih.gov/api/v1"
  },
  "qi_1": 0.002747218761321563,
  "qi_2": 0.007896277195504215,
  "rpve_csf": 25.779260403974362,
  "rpve_gm": 12.661679387068197,
  "rpve_wm": 17.682788145455163,
  "size_x": 160,
  "size_y": 256,
  "size_z": 256,
  "snr_csf": 3.4765853443650543,
  "snr_gm": 12.867941921148736,
  "snr_total": 14.521867579658952,
  "snr_wm": 27.221075473463063,
  "snrd_csf": 39.28355229287444,
  "snrd_gm": 78.78481593806848,
  "snrd_total": 73.23528460535242,
  "snrd_wm": 101.63748558511436,
  "spacing_x": 1.0,
  "spacing_y": 1.0,
  "spacing_z": 1.0,
  "summary_bg_k": 8.28166926583368,
  "summary_bg_mad": 6.445786952972412,
  "summary_bg_mean": 4.438133239746094,
  "summary_bg_median": 4.347617149353027,
  "summary_bg_n": 597494.0,
  "summary_bg_p05": 0.0,
  "summary_bg_p95": 13.118572616577149,
  "summary_bg_stdv": 4.954379081726074,
  "summary_csf_k": 14.488862390023499,
  "summary_csf_mad": 95.6042709350586,
  "summary_csf_mean": 416.9429626464844,
  "summary_csf_median": 386.5048828125,
  "summary_csf_n": 27472.0,
  "summary_csf_p05": 285.75079650878905,
  "summary_csf_p95": 611.0980010986328,
  "summary_csf_stdv": 111.17168426513672,
  "summary_gm_k": 0.3030144242523276,
  "summary_gm_mad": 56.542354583740234,
  "summary_gm_mean": 778.3054809570312,
  "summary_gm_median": 775.1517944335938,
  "summary_gm_n": 32204.0,
  "summary_gm_p05": 684.5386779785157,
  "summary_gm_p95": 886.4172119140625,
  "summary_gm_stdv": 60.23805236816406,
  "summary_wm_k": 1.3258868014164937,
  "summary_wm_mad": 32.55209732055664,
  "summary_wm_mean": 997.2659912109375,
  "summary_wm_median": 999.9957275390625,
  "summary_wm_n": 199603.0,
  "summary_wm_p05": 932.0564819335938,
  "summary_wm_p95": 1051.2684204101563,
  "summary_wm_stdv": 36.735992431640625,
  "tpm_overlap_csf": 0.23301145434379578,
  "tpm_overlap_gm": 0.5146161913871765,
  "tpm_overlap_wm": 0.5314463376998901,
  "wm2max": 0.6967740930980382
}