{
  "aor": 0.001011344827586207,
  "aqi": 0.006298327172413793,
  "bids_meta": {
    "EchoTime": 0.028,
    "EffectiveEchoSpacing": 0.0004491592855135947,
    "FlipAngle": 90,
    "NumberOfVolumesDiscardedByScanner": 1,
    "ParallelReductionFactorInPlane": 0,
    "PhaseEncodingDirection": "j",
    "PulseSequenceType": "gradient echo EPI",
    "RepetitionTime": 2.2,
    "SliceEncodingDirection": "i-",
    "SliceTiming": [
      0.0,
      0.0476,
      0.0952,
      0.1429,
      0.1905,
      0.2381,
      0.2857,
      0.3333,
      0.381,
      0.4286,
      0.4762,
      0.5238,
      0.5714,
      0.619,
      0.6667,
      0.7143,
      0.7619,
      0.8095,
      0.8571,
      0.9048,
      0.9524,
      1.0,
      1.0476,
      1.0952,
      1.1429,
      1.1905,
      1.2381,
      1.2857,
      1.3333,
      1.381,
      1.4286,
      1.4762,
      1.5238,
      1.5714,
      1.619,
      1.6667,
      1.7143,
      1.7619,
      1.8095,
      1.8571,
      1.9048,
      1.9524
    ],
    "TaskName": "moviewatching",
    "TotalReadoutTime": 0.028297034987356466,
    "WaterFatShift": 12.482,
    "dataset": "unknown",
    "modality": "bold",
    "subject_id": "0313",
    "task_id": "moviewatching"
  },
  "dummy_trs": 0,
  "dvars_nstd": 22.829755390242223,
  "dvars_std": 1.1784353607958478,
  "dvars_vstd": 0.9803309176124566,
  "efc": 0.5930331914508278,
  "fber": 6827275.0,
  "fd_mean": 0.2645064023374767,
  "fd_num": 176,
  "fd_perc": 60.689655172413794,
  "fwhm_avg": 2.506145465192103,
  "fwhm_x": 2.210436395576309,
  "fwhm_y": 2.876993333333333,
  "fwhm_z": 2.4310066666666668,
  "gcor": 0.0427814,
  "gsr_x": 0.022336959838867188,
  "gsr_y": 0.003910559229552746,
  "provenance": {
    "md5sum": "b9b36e64c9e36dc012d03a8fed97e6bf",
    "settings": {
      "fd_thres": 0.2,
      "hmc_fsl": false
    },
    "software": "mriqc",
    "version": "0.15.0",
    "webapi_port": null,
    "webapi_url": "https://mriqc.nimh.nih.gov/api/v1"
  },
  "size_t": 290,
  "size_x": 42,
  "size_y": 60,
  "size_z": 49,
  "snr": 4.900838059519201,
  "spacing_tr": 2.200000047683716,
  "spacing_x": 3.299999952316284,
  "spacing_y": 3.0,
  "spacing_z": 3.0,
  "spikes_num": 0,
  "summary_bg_k": 36.36520936075511,
  "summary_bg_mad": 0.12457267940044403,
  "summary_bg_mean": 5.956216335296631,
  "summary_bg_median": 0.09286288917064667,
  "summary_bg_n": 48024.0,
  "summary_bg_p05": 0.0017269624513573947,
  "summary_bg_p95": 32.41704769134521,
  "summary_bg_stdv": 19.611310958862305,
  "summary_fg_k": 2.466019314075351,
  "summary_fg_mad": 51.0970458984375,
  "summary_fg_mean": 309.6897888183594,
  "summary_fg_median": 309.33685302734375,
  "summary_fg_n": 42232.0,
  "summary_fg_p05": 210.28117904663088,
  "summary_fg_p95": 407.1013839721679,
  "summary_fg_stdv": 63.11842727661133,
  "tsnr": 57.669349670410156
}