{
  "bids_meta": {
    "EchoTime": 0.037,
    "FlipAngle": 8,
    "ParallelAcquisitionTechnique": "SENSE",
    "ParallelReductionFactorInPlan": [
      1,
      1.5
    ],
    "PhaseEncodingDirection": [
      "i-",
      "j-"
    ],
    "PulseSequenceType": "3D fast-field echo",
    "RepetitionTime": 0.081,
    "WaterFatShift": 2.268,
    "dataset": "unknown",
    "modality": "T1w",
    "run_id": 3,
    "subject_id": "0311"
  },
  "cjv": 0.40137967188325196,
  "cnr": 3.165445055715124,
  "efc": 0.636925216253029,
  "fber": 49323.6640625,
  "fwhm_avg": 4.275266666666666,
  "fwhm_x": 4.1088,
  "fwhm_y": 4.60962,
  "fwhm_z": 4.10738,
  "icvs_csf": 0.18860867838117165,
  "icvs_gm": 0.44026274293355,
  "icvs_wm": 0.3711285786852783,
  "inu_med": 0.7773709297180176,
  "inu_range": 0.25159152448177335,
  "provenance": {
    "md5sum": "76a8de22e4256d2d844bb8c6dd744ecd",
    "settings": {
      "testing": false
    },
    "software": "mriqc",
    "version": "0.15.0",
    "warnings": {
      "large_rot_frame": true,
      "small_air_mask": false
    },
    "webapi_port": null,
    "webapi_url": "https://mriqc.nimh.nih.gov/api/v1"
  },
  "qi_1": 0.021045506474981674,
  "qi_2": 0.00522884621562515,
  "rpve_csf": 27.40360658066791,
  "rpve_gm": 12.845824009383383,
  "rpve_wm": 17.34559724266207,
  "size_x": 160,
  "size_y": 256,
  "size_z": 256,
  "snr_csf": 3.1350363655927596,
  "snr_gm": 13.635860245180188,
  "snr_total": 14.800800133364241,
  "snr_wm": 27.631503789319776,
  "snrd_csf": 60.418385018795334,
  "snrd_gm": 119.15490816745603,
  "snrd_total": 110.4889847961191,
  "snrd_wm": 151.8936612021059,
  "spacing_x": 1.0,
  "spacing_y": 1.0,
  "spacing_z": 1.0,
  "summary_bg_k": 9.731269640910984,
  "summary_bg_mad": 4.313127040863037,
  "summary_bg_mean": 3.57772159576416,
  "summary_bg_median": 2.9091598987579346,
  "summary_bg_n": 825605.0,
  "summary_bg_p05": 0.0,
  "summary_bg_p95": 11.636244583129882,
  "summary_bg_stdv": 4.130459308624268,
  "summary_csf_k": 22.527966178842128,
  "summary_csf_mad": 103.2944564819336,
  "summary_csf_mean": 431.5691223144531,
  "summary_csf_median": 397.767822265625,
  "summary_csf_n": 27301.0,
  "summary_csf_p05": 292.15692138671875,
  "summary_csf_p95": 627.7247314453125,
  "summary_csf_stdv": 126.87589263916016,
  "summary_gm_k": 0.2822529279276713,
  "summary_gm_mad": 55.508087158203125,
  "summary_gm_mean": 786.8989868164062,
  "summary_gm_median": 784.4630126953125,
  "summary_gm_n": 32785.0,
  "summary_gm_p05": 696.4953125000001,
  "summary_gm_p95": 885.9656249999999,
  "summary_gm_stdv": 57.528533935546875,
  "summary_wm_k": 1.3678082326746912,
  "summary_wm_mad": 31.004249572753906,
  "summary_wm_mean": 996.8162841796875,
  "summary_wm_median": 1000.0004272460938,
  "summary_wm_n": 205805.0,
  "summary_wm_p05": 929.6387939453125,
  "summary_wm_p95": 1048.8439697265626,
  "summary_wm_stdv": 36.19050216674805,
  "tpm_overlap_csf": 0.2255256175994873,
  "tpm_overlap_gm": 0.5219532251358032,
  "tpm_overlap_wm": 0.5480762124061584,
  "wm2max": 0.6962188110171733
}