{
  "aor": 0.0015784137931034484,
  "aqi": 0.0037751626896551727,
  "bids_meta": {
    "EchoTime": 0.028,
    "EffectiveEchoSpacing": 0.0004491592855135947,
    "FlipAngle": 90,
    "NumberOfVolumesDiscardedByScanner": 1,
    "ParallelReductionFactorInPlane": 0,
    "PhaseEncodingDirection": "j",
    "PulseSequenceType": "gradient echo EPI",
    "RepetitionTime": 2.2,
    "SliceEncodingDirection": "i-",
    "SliceTiming": [
      0.0,
      0.0476,
      0.0952,
      0.1429,
      0.1905,
      0.2381,
      0.2857,
      0.3333,
      0.381,
      0.4286,
      0.4762,
      0.5238,
      0.5714,
      0.619,
      0.6667,
      0.7143,
      0.7619,
      0.8095,
      0.8571,
      0.9048,
      0.9524,
      1.0,
      1.0476,
      1.0952,
      1.1429,
      1.1905,
      1.2381,
      1.2857,
      1.3333,
      1.381,
      1.4286,
      1.4762,
      1.5238,
      1.5714,
      1.619,
      1.6667,
      1.7143,
      1.7619,
      1.8095,
      1.8571,
      1.9048,
      1.9524
    ],
    "TaskName": "moviewatching",
    "TotalReadoutTime": 0.028297034987356466,
    "WaterFatShift": 12.482,
    "dataset": "unknown",
    "modality": "bold",
    "subject_id": "0918",
    "task_id": "moviewatching"
  },
  "dummy_trs": 0,
  "dvars_nstd": 21.515704825017302,
  "dvars_std": 1.2540671816955027,
  "dvars_vstd": 1.003051981211072,
  "efc": 0.5266232506470016,
  "fber": 27837078.0,
  "fd_mean": 0.12072443386931808,
  "fd_num": 27,
  "fd_perc": 9.310344827586206,
  "fwhm_avg": 2.422675061141964,
  "fwhm_x": 2.2084151834258914,
  "fwhm_y": 2.737636666666667,
  "fwhm_z": 2.3219733333333332,
  "gcor": 0.0597444,
  "gsr_x": 0.04618103802204132,
  "gsr_y": 0.0032772445119917393,
  "provenance": {
    "md5sum": "618bb330603090abeaa8fee7bb799ec1",
    "settings": {
      "fd_thres": 0.2,
      "hmc_fsl": false
    },
    "software": "mriqc",
    "version": "0.15.0",
    "webapi_port": null,
    "webapi_url": "https://mriqc.nimh.nih.gov/api/v1"
  },
  "size_t": 290,
  "size_x": 42,
  "size_y": 64,
  "size_z": 51,
  "snr": 4.9719318927693195,
  "spacing_tr": 2.200000047683716,
  "spacing_x": 3.299999952316284,
  "spacing_y": 3.0,
  "spacing_z": 3.0,
  "spikes_num": 0,
  "summary_bg_k": 63.344334563887486,
  "summary_bg_mad": 9.431429862976074,
  "summary_bg_mean": 730.4527587890625,
  "summary_bg_median": 6.55552864074707,
  "summary_bg_n": 66181.0,
  "summary_bg_p05": 0.05628766492009163,
  "summary_bg_p95": 3971.95166015625,
  "summary_bg_stdv": 2893.07958984375,
  "summary_fg_k": 2.51264395239693,
  "summary_fg_mad": 7301.955078125,
  "summary_fg_mean": 41979.7578125,
  "summary_fg_median": 41998.515625,
  "summary_fg_n": 37284.0,
  "summary_fg_p05": 28685.674023437503,
  "summary_fg_p95": 54422.714062499996,
  "summary_fg_stdv": 8447.0087890625,
  "tsnr": 70.87781524658203
}