{
  "bids_meta": {
    "EchoTime": 0.037,
    "FlipAngle": 8,
    "ParallelAcquisitionTechnique": "SENSE",
    "ParallelReductionFactorInPlan": [
      1,
      1.5
    ],
    "PhaseEncodingDirection": [
      "i-",
      "j-"
    ],
    "PulseSequenceType": "3D fast-field echo",
    "RepetitionTime": 0.081,
    "WaterFatShift": 2.268,
    "dataset": "unknown",
    "modality": "T1w",
    "run_id": 3,
    "subject_id": "0863"
  },
  "cjv": 0.5635763447016661,
  "cnr": 2.224085281298478,
  "efc": 0.752929667286974,
  "fber": 16370.7587890625,
  "fwhm_avg": 4.28066,
  "fwhm_x": 4.13614,
  "fwhm_y": 4.59156,
  "fwhm_z": 4.11428,
  "icvs_csf": 0.21734396117662944,
  "icvs_gm": 0.4144330481264337,
  "icvs_wm": 0.3682229906969368,
  "inu_med": 0.6934554576873779,
  "inu_range": 0.2672882616519927,
  "provenance": {
    "md5sum": "8dae341b9a633c19aa7c07adb0feb9df",
    "settings": {
      "testing": false
    },
    "software": "mriqc",
    "version": "0.15.0",
    "warnings": {
      "large_rot_frame": true,
      "small_air_mask": false
    },
    "webapi_port": null,
    "webapi_url": "https://mriqc.nimh.nih.gov/api/v1"
  },
  "qi_1": 0.0,
  "qi_2": 0.004639615326454263,
  "rpve_csf": 20.48559859002212,
  "rpve_gm": 11.122882243111691,
  "rpve_wm": 14.92205093766457,
  "size_x": 160,
  "size_y": 256,
  "size_z": 256,
  "snr_csf": 2.6141682466918144,
  "snr_gm": 9.28829492751224,
  "snr_total": 12.754337437314904,
  "snr_wm": 26.36054913774066,
  "snrd_csf": 31.13452953734279,
  "snrd_gm": 66.51019758392344,
  "snrd_total": 60.56641182847748,
  "snrd_wm": 84.05450836416621,
  "spacing_x": 1.0,
  "spacing_y": 1.0,
  "spacing_z": 1.0,
  "summary_bg_k": 7.023876247640176,
  "summary_bg_mad": 7.794264793395996,
  "summary_bg_mean": 9.653571128845215,
  "summary_bg_median": 5.2571516036987305,
  "summary_bg_n": 416896.0,
  "summary_bg_p05": 0.0,
  "summary_bg_p95": 31.383618354797363,
  "summary_bg_stdv": 10.543888092041016,
  "summary_csf_k": 47.646241905252154,
  "summary_csf_mad": 102.62097930908203,
  "summary_csf_mean": 407.23699951171875,
  "summary_csf_median": 370.41259765625,
  "summary_csf_n": 38666.0,
  "summary_csf_p05": 263.8920135498047,
  "summary_csf_p95": 624.0758819580078,
  "summary_csf_stdv": 141.69241333007812,
  "summary_gm_k": 0.007482956168068711,
  "summary_gm_mad": 82.23469543457031,
  "summary_gm_mean": 800.0507202148438,
  "summary_gm_median": 791.28271484375,
  "summary_gm_n": 25116.0,
  "summary_gm_p05": 674.7074584960938,
  "summary_gm_p95": 957.293212890625,
  "summary_gm_stdv": 85.18968963623047,
  "summary_wm_k": 0.6176619921567066,
  "summary_wm_mad": 35.399208068847656,
  "summary_wm_mean": 999.9469604492188,
  "summary_wm_median": 1000.01025390625,
  "summary_wm_n": 241395.0,
  "summary_wm_p05": 937.3224060058594,
  "summary_wm_p95": 1061.655029296875,
  "summary_wm_stdv": 37.935787200927734,
  "tpm_overlap_csf": 0.2407202571630478,
  "tpm_overlap_gm": 0.5094488859176636,
  "tpm_overlap_wm": 0.5534632802009583,
  "wm2max": 0.6543320352481404
}