{
  "bids_meta": {
    "EchoTime": 0.037,
    "FlipAngle": 8,
    "ParallelAcquisitionTechnique": "SENSE",
    "ParallelReductionFactorInPlan": [
      1,
      1.5
    ],
    "PhaseEncodingDirection": [
      "i-",
      "j-"
    ],
    "PulseSequenceType": "3D fast-field echo",
    "RepetitionTime": 0.081,
    "WaterFatShift": 2.268,
    "dataset": "unknown",
    "modality": "T1w",
    "run_id": 3,
    "subject_id": "0643"
  },
  "cjv": 0.4116646791686504,
  "cnr": 3.018741422047838,
  "efc": 0.6693269946380919,
  "fber": 29037.650390625,
  "fwhm_avg": 4.221963333333333,
  "fwhm_x": 4.08865,
  "fwhm_y": 4.63256,
  "fwhm_z": 3.94468,
  "icvs_csf": 0.16433391074450224,
  "icvs_gm": 0.4472661565689412,
  "icvs_wm": 0.3883999326865566,
  "inu_med": 1.0404372215270996,
  "inu_range": 0.34614312648773193,
  "provenance": {
    "md5sum": "2bcb4635dc77eede132d454dcfc7cd48",
    "settings": {
      "testing": false
    },
    "software": "mriqc",
    "version": "0.15.0",
    "warnings": {
      "large_rot_frame": true,
      "small_air_mask": false
    },
    "webapi_port": null,
    "webapi_url": "https://mriqc.nimh.nih.gov/api/v1"
  },
  "qi_1": 0.010105423467560753,
  "qi_2": 0.005224804594720419,
  "rpve_csf": 31.823325688003347,
  "rpve_gm": 13.382778957118148,
  "rpve_wm": 17.581834887798156,
  "size_x": 160,
  "size_y": 256,
  "size_z": 256,
  "snr_csf": 2.817302165456304,
  "snr_gm": 11.340369854690655,
  "snr_total": 14.289365128547628,
  "snr_wm": 28.71042336549592,
  "snrd_csf": 38.82897994456564,
  "snrd_gm": 82.26103917282934,
  "snrd_total": 76.01509380068727,
  "snrd_wm": 106.9552622846668,
  "spacing_x": 1.0,
  "spacing_y": 1.0,
  "spacing_z": 1.0,
  "summary_bg_k": 6.174898402700451,
  "summary_bg_mad": 6.125355243682861,
  "summary_bg_mean": 5.43673849105835,
  "summary_bg_median": 4.131489276885986,
  "summary_bg_n": 631108.0,
  "summary_bg_p05": 0.0,
  "summary_bg_p95": 16.61814088821411,
  "summary_bg_stdv": 6.080892086029053,
  "summary_csf_k": 25.69730741241491,
  "summary_csf_mad": 68.85535430908203,
  "summary_csf_mean": 409.8846740722656,
  "summary_csf_median": 363.0408935546875,
  "summary_csf_n": 23128.0,
  "summary_csf_p05": 294.199641418457,
  "summary_csf_p95": 623.3498931884762,
  "summary_csf_stdv": 128.8583984375,
  "summary_gm_k": 0.19443045608352216,
  "summary_gm_mad": 64.94578552246094,
  "summary_gm_mean": 778.6026611328125,
  "summary_gm_median": 769.119384765625,
  "summary_gm_n": 36372.0,
  "summary_gm_p05": 684.46162109375,
  "summary_gm_p95": 904.8672119140624,
  "summary_gm_stdv": 67.8204345703125,
  "summary_wm_k": 1.3874722313589407,
  "summary_wm_mad": 30.101242065429688,
  "summary_wm_mean": 997.4564208984375,
  "summary_wm_median": 1000.0039672851562,
  "summary_wm_n": 203670.0,
  "summary_wm_p05": 935.6522552490235,
  "summary_wm_p95": 1048.7103576660156,
  "summary_wm_stdv": 34.83060836791992,
  "tpm_overlap_csf": 0.252200722694397,
  "tpm_overlap_gm": 0.5312609076499939,
  "tpm_overlap_wm": 0.5577067136764526,
  "wm2max": 0.6605548346550443
}