{
  "bids_meta": {
    "EchoTime": 0.037,
    "FlipAngle": 8,
    "ParallelAcquisitionTechnique": "SENSE",
    "ParallelReductionFactorInPlan": [
      1,
      1.5
    ],
    "PhaseEncodingDirection": [
      "i-",
      "j-"
    ],
    "PulseSequenceType": "3D fast-field echo",
    "RepetitionTime": 0.081,
    "WaterFatShift": 2.268,
    "dataset": "unknown",
    "modality": "T1w",
    "run_id": 3,
    "subject_id": "0069"
  },
  "cjv": 0.42724350873087497,
  "cnr": 3.0485535271113293,
  "efc": 0.6385391206517039,
  "fber": 38626.328125,
  "fwhm_avg": 4.296736666666667,
  "fwhm_x": 4.12409,
  "fwhm_y": 4.6993,
  "fwhm_z": 4.06682,
  "icvs_csf": 0.186187407182138,
  "icvs_gm": 0.4201754207319985,
  "icvs_wm": 0.3936371720858636,
  "inu_med": 1.6531552076339722,
  "inu_range": 0.5698685348033905,
  "provenance": {
    "md5sum": "e8fb9a36097dce310ab7b92fa7a73394",
    "settings": {
      "testing": false
    },
    "software": "mriqc",
    "version": "0.15.0",
    "warnings": {
      "large_rot_frame": true,
      "small_air_mask": false
    },
    "webapi_port": null,
    "webapi_url": "https://mriqc.nimh.nih.gov/api/v1"
  },
  "qi_1": 0.013215832838859352,
  "qi_2": 0.002925032517666739,
  "rpve_csf": 26.36551593082916,
  "rpve_gm": 12.673963204339875,
  "rpve_wm": 16.134974662109776,
  "size_x": 160,
  "size_y": 256,
  "size_z": 256,
  "snr_csf": 3.419254795525715,
  "snr_gm": 11.191510114497248,
  "snr_total": 14.258997729845689,
  "snr_wm": 28.166228279514105,
  "snrd_csf": 53.041754182673,
  "snrd_gm": 104.13949445849244,
  "snrd_total": 97.83223195895896,
  "snrd_wm": 136.31544723571142,
  "spacing_x": 1.0,
  "spacing_y": 1.0,
  "spacing_z": 1.0,
  "summary_bg_k": 313.82842914526367,
  "summary_bg_mad": 4.806061744689941,
  "summary_bg_mean": 5.762106895446777,
  "summary_bg_median": 3.2416393756866455,
  "summary_bg_n": 972747.0,
  "summary_bg_p05": 0.0,
  "summary_bg_p95": 19.758551597595215,
  "summary_bg_stdv": 8.652660369873047,
  "summary_csf_k": 13.328788999565813,
  "summary_csf_mad": 104.84944915771484,
  "summary_csf_mean": 406.7165222167969,
  "summary_csf_median": 389.11279296875,
  "summary_csf_n": 20058.0,
  "summary_csf_p05": 262.48639221191405,
  "summary_csf_p95": 601.1526000976559,
  "summary_csf_stdv": 113.7976303100586,
  "summary_gm_k": -0.053169680878955905,
  "summary_gm_mad": 69.10298156738281,
  "summary_gm_mean": 769.2261962890625,
  "summary_gm_median": 763.96435546875,
  "summary_gm_n": 26311.0,
  "summary_gm_p05": 667.1325073242188,
  "summary_gm_p95": 889.8341979980469,
  "summary_gm_stdv": 68.26155090332031,
  "summary_wm_k": 1.099509291633363,
  "summary_wm_mad": 31.744375228881836,
  "summary_wm_mean": 997.4837036132812,
  "summary_wm_median": 1000.0062255859375,
  "summary_wm_n": 228443.0,
  "summary_wm_p05": 934.7272583007813,
  "summary_wm_p95": 1049.9576660156251,
  "summary_wm_stdv": 35.50365447998047,
  "tpm_overlap_csf": 0.24635399878025055,
  "tpm_overlap_gm": 0.521159291267395,
  "tpm_overlap_wm": 0.5656486749649048,
  "wm2max": 0.6930262120437155
}