{
  "bids_meta": {
    "EchoTime": 0.037,
    "FlipAngle": 8,
    "ParallelAcquisitionTechnique": "SENSE",
    "ParallelReductionFactorInPlan": [
      1,
      1.5
    ],
    "PhaseEncodingDirection": [
      "i-",
      "j-"
    ],
    "PulseSequenceType": "3D fast-field echo",
    "RepetitionTime": 0.081,
    "WaterFatShift": 2.268,
    "dataset": "unknown",
    "modality": "T1w",
    "run_id": 2,
    "subject_id": "0113"
  },
  "cjv": 0.4858349600190182,
  "cnr": 2.7307990735998104,
  "efc": 0.738964720471738,
  "fber": 27188.984375,
  "fwhm_avg": 4.409216666666667,
  "fwhm_x": 4.23663,
  "fwhm_y": 4.79468,
  "fwhm_z": 4.19634,
  "icvs_csf": 0.1926898333778528,
  "icvs_gm": 0.4290937094774126,
  "icvs_wm": 0.37821645714473456,
  "inu_med": 1.328904390335083,
  "inu_range": 0.4690476417541505,
  "provenance": {
    "md5sum": "8e2bb8dee6c6b39b59e625225a8a7b72",
    "settings": {
      "testing": false
    },
    "software": "mriqc",
    "version": "0.15.0",
    "warnings": {
      "large_rot_frame": true,
      "small_air_mask": false
    },
    "webapi_port": null,
    "webapi_url": "https://mriqc.nimh.nih.gov/api/v1"
  },
  "qi_1": 0.008169978638232179,
  "qi_2": 0.00647579697079664,
  "rpve_csf": 22.968917522586572,
  "rpve_gm": 11.075784212544178,
  "rpve_wm": 14.471183821225939,
  "size_x": 160,
  "size_y": 256,
  "size_z": 256,
  "snr_csf": 3.58417932109713,
  "snr_gm": 11.693760759526466,
  "snr_total": 13.968560575044833,
  "snr_wm": 26.6277416445109,
  "snrd_csf": 39.37009346420105,
  "snrd_gm": 85.68492319932956,
  "snrd_total": 77.91025431681787,
  "snrd_wm": 108.67574628692302,
  "spacing_x": 1.0,
  "spacing_y": 1.0,
  "spacing_z": 1.0,
  "summary_bg_k": 4.955462118153001,
  "summary_bg_mad": 6.0284318923950195,
  "summary_bg_mean": 6.3909101486206055,
  "summary_bg_median": 4.066115379333496,
  "summary_bg_n": 524461.0,
  "summary_bg_p05": 0.0,
  "summary_bg_p95": 20.37358283996582,
  "summary_bg_stdv": 6.727842330932617,
  "summary_csf_k": 6.146954760000854,
  "summary_csf_mad": 74.04450988769531,
  "summary_csf_mean": 388.0313720703125,
  "summary_csf_median": 362.2756042480469,
  "summary_csf_n": 41525.0,
  "summary_csf_p05": 270.2659545898438,
  "summary_csf_p95": 589.9033569335937,
  "summary_csf_stdv": 101.07508850097656,
  "summary_gm_k": -0.013448567163203418,
  "summary_gm_mad": 67.24588012695312,
  "summary_gm_mean": 792.7188720703125,
  "summary_gm_median": 788.4552612304688,
  "summary_gm_n": 38034.0,
  "summary_gm_p05": 689.8827697753907,
  "summary_gm_p95": 910.8226165771484,
  "summary_gm_stdv": 67.42440795898438,
  "summary_wm_k": 0.45896186298791886,
  "summary_wm_mad": 35.535850524902344,
  "summary_wm_mean": 999.4755249023438,
  "summary_wm_median": 1000.0121459960938,
  "summary_wm_n": 247722.0,
  "summary_wm_p05": 936.6496337890625,
  "summary_wm_p95": 1060.1531860351563,
  "summary_wm_stdv": 37.555198669433594,
  "tpm_overlap_csf": 0.2445816844701767,
  "tpm_overlap_gm": 0.5151132345199585,
  "tpm_overlap_wm": 0.5523160696029663,
  "wm2max": 0.6407956172811078
}