{
  "bids_meta": {
    "EchoTime": 0.037,
    "FlipAngle": 8,
    "ParallelAcquisitionTechnique": "SENSE",
    "ParallelReductionFactorInPlan": [
      1,
      1.5
    ],
    "PhaseEncodingDirection": [
      "i-",
      "j-"
    ],
    "PulseSequenceType": "3D fast-field echo",
    "RepetitionTime": 0.081,
    "WaterFatShift": 2.268,
    "dataset": "unknown",
    "modality": "T1w",
    "run_id": 1,
    "subject_id": "0768"
  },
  "cjv": 0.4902834263064288,
  "cnr": 2.4884528059531372,
  "efc": 0.7819852040627103,
  "fber": 14598.9208984375,
  "fwhm_avg": 4.341173333333333,
  "fwhm_x": 4.21864,
  "fwhm_y": 4.7321,
  "fwhm_z": 4.07278,
  "icvs_csf": 0.2222863620692426,
  "icvs_gm": 0.424170846283114,
  "icvs_wm": 0.3535427916476434,
  "inu_med": 1.0180944204330444,
  "inu_range": 0.4268776655197144,
  "provenance": {
    "md5sum": "39867b415618d24d3123fa526f66b1e8",
    "settings": {
      "testing": false
    },
    "software": "mriqc",
    "version": "0.15.0",
    "warnings": {
      "large_rot_frame": true,
      "small_air_mask": false
    },
    "webapi_port": null,
    "webapi_url": "https://mriqc.nimh.nih.gov/api/v1"
  },
  "qi_1": 0.0012651913580353459,
  "qi_2": 0.01047646728878058,
  "rpve_csf": 19.08065152992729,
  "rpve_gm": 10.35110504401881,
  "rpve_wm": 14.354872800867565,
  "size_x": 160,
  "size_y": 256,
  "size_z": 256,
  "snr_csf": 2.63120728388076,
  "snr_gm": 11.35470641608563,
  "snr_total": 13.15804019201076,
  "snr_wm": 25.488206876065895,
  "snrd_csf": 31.187553760003183,
  "snrd_gm": 67.4862177142409,
  "snrd_total": 61.04920448754823,
  "snrd_wm": 84.47384198840064,
  "spacing_x": 1.0,
  "spacing_y": 1.0,
  "spacing_z": 1.0,
  "summary_bg_k": 70.27620782569717,
  "summary_bg_mad": 7.755612373352051,
  "summary_bg_mean": 5.876602649688721,
  "summary_bg_median": 5.231081008911133,
  "summary_bg_n": 320530.0,
  "summary_bg_p05": 0.0,
  "summary_bg_p95": 15.975613212585449,
  "summary_bg_stdv": 6.425518035888672,
  "summary_csf_k": 66.15523939286517,
  "summary_csf_mad": 76.59928894042969,
  "summary_csf_mean": 406.8837890625,
  "summary_csf_median": 369.2033996582031,
  "summary_csf_n": 51051.0,
  "summary_csf_p05": 283.2698516845703,
  "summary_csf_p95": 616.2020568847656,
  "summary_csf_stdv": 140.31573486328125,
  "summary_gm_k": 0.6792540652999461,
  "summary_gm_mad": 63.60923767089844,
  "summary_gm_mean": 804.552734375,
  "summary_gm_median": 798.9129638671875,
  "summary_gm_n": 29812.0,
  "summary_gm_p05": 698.8700897216797,
  "summary_gm_p95": 933.7340148925781,
  "summary_gm_stdv": 70.35845184326172,
  "summary_wm_k": 1.001368629331778,
  "summary_wm_mad": 34.987884521484375,
  "summary_wm_mean": 999.019775390625,
  "summary_wm_median": 1000.0152587890625,
  "summary_wm_n": 241230.0,
  "summary_wm_p05": 931.9276245117187,
  "summary_wm_p95": 1061.1223266601562,
  "summary_wm_stdv": 39.23434829711914,
  "tpm_overlap_csf": 0.22797024250030518,
  "tpm_overlap_gm": 0.4986169934272766,
  "tpm_overlap_wm": 0.5359964370727539,
  "wm2max": 0.6063975643022935
}