{
  "bids_meta": {
    "EchoTime": 0.037,
    "FlipAngle": 8,
    "ParallelAcquisitionTechnique": "SENSE",
    "ParallelReductionFactorInPlan": [
      1,
      1.5
    ],
    "PhaseEncodingDirection": [
      "i-",
      "j-"
    ],
    "PulseSequenceType": "3D fast-field echo",
    "RepetitionTime": 0.081,
    "WaterFatShift": 2.268,
    "dataset": "unknown",
    "modality": "T1w",
    "run_id": 1,
    "subject_id": "0553"
  },
  "cjv": 0.599043863876366,
  "cnr": 2.119814627210358,
  "efc": 0.8081405609038559,
  "fber": 13966.5439453125,
  "fwhm_avg": 4.322093333333334,
  "fwhm_x": 4.19464,
  "fwhm_y": 4.62753,
  "fwhm_z": 4.14411,
  "icvs_csf": 0.19544377487320105,
  "icvs_gm": 0.4330208021328766,
  "icvs_wm": 0.37153542299392234,
  "inu_med": 0.8517903089523315,
  "inu_range": 0.3711768090724945,
  "provenance": {
    "md5sum": "d44d74af24c527e16956e6f84b0f3348",
    "settings": {
      "testing": false
    },
    "software": "mriqc",
    "version": "0.15.0",
    "warnings": {
      "large_rot_frame": true,
      "small_air_mask": true
    },
    "webapi_port": null,
    "webapi_url": "https://mriqc.nimh.nih.gov/api/v1"
  },
  "qi_1": 0.0002573488329569042,
  "qi_2": 0.009773243407688323,
  "rpve_csf": 21.924836952740016,
  "rpve_gm": 10.649172064300387,
  "rpve_wm": 14.364998603958124,
  "size_x": 160,
  "size_y": 256,
  "size_z": 256,
  "snr_csf": 2.29971897586878,
  "snr_gm": 10.117469709325132,
  "snr_total": 11.88563967882738,
  "snr_wm": 23.239730351288223,
  "snrd_csf": 32.29560814173622,
  "snrd_gm": 59.86486702583662,
  "snrd_total": 55.43636010992981,
  "snrd_wm": 74.14860516221658,
  "spacing_x": 1.0,
  "spacing_y": 1.0,
  "spacing_z": 1.0,
  "summary_bg_k": 3.4602915412492177,
  "summary_bg_mad": 8.835619926452637,
  "summary_bg_mean": 6.1666412353515625,
  "summary_bg_median": 5.959534645080566,
  "summary_bg_n": 112171.0,
  "summary_bg_p05": 0.0,
  "summary_bg_p95": 17.951987266540527,
  "summary_bg_stdv": 6.237423419952393,
  "summary_csf_k": 30.45084646703529,
  "summary_csf_mad": 147.3524169921875,
  "summary_csf_mean": 476.56353759765625,
  "summary_csf_median": 435.560791015625,
  "summary_csf_n": 28223.0,
  "summary_csf_p05": 290.7399505615234,
  "summary_csf_p95": 697.2610107421874,
  "summary_csf_stdv": 189.39404296875,
  "summary_gm_k": 0.18795878412996014,
  "summary_gm_mad": 77.15177917480469,
  "summary_gm_mean": 814.9688110351562,
  "summary_gm_median": 807.3787841796875,
  "summary_gm_n": 33204.0,
  "summary_gm_p05": 698.3046264648438,
  "summary_gm_p95": 961.3581329345703,
  "summary_gm_stdv": 79.79926300048828,
  "summary_wm_k": 0.8864144660030924,
  "summary_wm_mad": 38.24822235107422,
  "summary_wm_mean": 999.063232421875,
  "summary_wm_median": 1000.0191040039062,
  "summary_wm_n": 248696.0,
  "summary_wm_p05": 924.4717559814453,
  "summary_wm_p95": 1067.0927734375,
  "summary_wm_stdv": 43.030494689941406,
  "tpm_overlap_csf": 0.2073579728603363,
  "tpm_overlap_gm": 0.49768903851509094,
  "tpm_overlap_wm": 0.5241391658782959,
  "wm2max": 0.6072199078125625
}