{
  "bids_meta": {
    "EchoTime": 0.037,
    "FlipAngle": 8,
    "ParallelAcquisitionTechnique": "SENSE",
    "ParallelReductionFactorInPlan": [
      1,
      1.5
    ],
    "PhaseEncodingDirection": [
      "i-",
      "j-"
    ],
    "PulseSequenceType": "3D fast-field echo",
    "RepetitionTime": 0.081,
    "WaterFatShift": 2.268,
    "dataset": "unknown",
    "modality": "T1w",
    "run_id": 2,
    "subject_id": "0353"
  },
  "cjv": 0.42738658660712625,
  "cnr": 2.8501303904177946,
  "efc": 0.7122462743681994,
  "fber": 30933.6953125,
  "fwhm_avg": 4.498896666666667,
  "fwhm_x": 4.41302,
  "fwhm_y": 4.82626,
  "fwhm_z": 4.25741,
  "icvs_csf": 0.18733012324110768,
  "icvs_gm": 0.4464935518990689,
  "icvs_wm": 0.3661763248598234,
  "inu_med": 1.1341520547866821,
  "inu_range": 0.4612374067306517,
  "provenance": {
    "md5sum": "d5d1fd24ba7f61e320061242fd08d8b4",
    "settings": {
      "testing": false
    },
    "software": "mriqc",
    "version": "0.15.0",
    "warnings": {
      "large_rot_frame": true,
      "small_air_mask": false
    },
    "webapi_port": null,
    "webapi_url": "https://mriqc.nimh.nih.gov/api/v1"
  },
  "qi_1": 0.017448140650837368,
  "qi_2": 0.01770501540727655,
  "rpve_csf": 24.163405326687556,
  "rpve_gm": 11.233501294283048,
  "rpve_wm": 15.49546085274264,
  "size_x": 160,
  "size_y": 256,
  "size_z": 256,
  "snr_csf": 3.1443245253888135,
  "snr_gm": 10.851947774517399,
  "snr_total": 12.877872001254188,
  "snr_wm": 24.63734370385635,
  "snrd_csf": 48.79542275142371,
  "snrd_gm": 86.30905647279283,
  "snrd_total": 82.55412096052405,
  "snrd_wm": 112.5578836573556,
  "spacing_x": 1.0,
  "spacing_y": 1.0,
  "spacing_z": 1.0,
  "summary_bg_k": 102.17621335108984,
  "summary_bg_mad": 5.820479869842529,
  "summary_bg_mean": 5.254444122314453,
  "summary_bg_median": 3.961487054824829,
  "summary_bg_n": 617302.0,
  "summary_bg_p05": 0.0,
  "summary_bg_p95": 15.768677711486816,
  "summary_bg_stdv": 7.394534111022949,
  "summary_csf_k": 20.032341192908437,
  "summary_csf_mad": 119.96189880371094,
  "summary_csf_mean": 462.1029052734375,
  "summary_csf_median": 433.51702880859375,
  "summary_csf_n": 30518.0,
  "summary_csf_p05": 296.8083755493164,
  "summary_csf_p95": 664.8850128173829,
  "summary_csf_stdv": 137.87060546875,
  "summary_gm_k": 0.3471884618617782,
  "summary_gm_mad": 65.17337036132812,
  "summary_gm_mean": 777.7509155273438,
  "summary_gm_median": 766.8023681640625,
  "summary_gm_n": 40738.0,
  "summary_gm_p05": 679.8609283447265,
  "summary_gm_p95": 912.005581665039,
  "summary_gm_stdv": 70.65947723388672,
  "summary_wm_k": 1.45884368236129,
  "summary_wm_mad": 34.4951171875,
  "summary_wm_mean": 995.8737182617188,
  "summary_wm_median": 1000.0068969726562,
  "summary_wm_n": 226656.0,
  "summary_wm_p05": 919.9978942871094,
  "summary_wm_p95": 1053.8099365234375,
  "summary_wm_stdv": 40.58898162841797,
  "tpm_overlap_csf": 0.202537402510643,
  "tpm_overlap_gm": 0.5014980435371399,
  "tpm_overlap_wm": 0.5109294652938843,
  "wm2max": 0.6312110702652921
}